EasySelenium/__init__.py
EasySelenium/common/__init__.py
EasySelenium/common/utils.py
EasySelenium/proxy/__init__.py
EasySelenium/proxy/proxy.py
EasySelenium/proxy/utils.py
EasySelenium/proxy/addon/__init__.py
EasySelenium/proxy/addon/base.py
EasySelenium/webdriver/__init__.py
EasySelenium/webdriver/driver.py
EasySelenium/webdriver/utils.py
Easy2Selenium-0.0.1.dist-info/LICENSE
Easy2Selenium-0.0.1.dist-info/METADATA
Easy2Selenium-0.0.1.dist-info/WHEEL
Easy2Selenium-0.0.1.dist-info/top_level.txt
Easy2Selenium-0.0.1.dist-info/RECORD
