Metadata-Version: 2.1
Name: Easy2Selenium
Version: 0.0.1
Summary: Library for easy use of Selenium.
Home-page: https://github.com/HHongSeungWoo/EasySelenium
Author: HHongSeungWoo
Author-email: qksn1541@gmail.com
License: UNKNOWN
Platform: UNKNOWN
Classifier: License :: OSI Approved :: MIT License
Requires-Python: >=3.0
Requires-Dist: selenium
Requires-Dist: mitmproxy
